histographer/analysis/image/__init__.py
histographer/analysis/image/align.py
histographer/analysis/image/analysis.py
histographer/analysis/image/color.py
histographer/analysis/image/fetch.py
histographer/analysis/image/high_level.py
histographer/analysis/image/segment.py
histographer/analysis/image/tissue_detect.py
histographer/analysis/ranking/__init__.py
histographer/analysis/ranking/algorithms.py
histographer/analysis/ranking/error.py
histographer/analysis/ranking/format.py
histographer/analysis/ranking/high_level.py
histographer/analysis/ranking/mock.py
histographer/analysis/ranking/testing.py
histographer_analysis-1.0.1.dist-info/LICENSE
histographer_analysis-1.0.1.dist-info/METADATA
histographer_analysis-1.0.1.dist-info/WHEEL
histographer_analysis-1.0.1.dist-info/top_level.txt
histographer_analysis-1.0.1.dist-info/RECORD
